[
    {
        "fecha": "2023-06-23",
        "nombre": "davines oi champ\u00fa 280 ml",
        "GSI": "14195707237233699508",
        "historicos": {
            "Amazon.es - Seller": [
                {
                    "fecha": "2023-06-23",
                    "precio": 20.8
                }
            ],
            "davines-ah.com": [
                {
                    "fecha": "2023-06-23",
                    "precio": 12.01
                }
            ],
            "anadeana": [
                {
                    "fecha": "2023-06-23",
                    "precio": 29.61
                }
            ],
            "Notino.es": [
                {
                    "fecha": "2023-06-23",
                    "precio": 30.08
                }
            ],
            "Peluquer\u00eda Wapa\u00b4s": [
                {
                    "fecha": "2023-06-23",
                    "precio": 21.07
                }
            ],
            "Beauty Hair": [
                {
                    "fecha": "2023-06-23",
                    "precio": 28.84
                }
            ],
            ".Prohair Store": [
                {
                    "fecha": "2023-06-23",
                    "precio": 28.03
                }
            ],
            "Sm The Beauty": [
                {
                    "fecha": "2023-06-23",
                    "precio": 37.87
                }
            ],
            "hairllowers.com": [
                {
                    "fecha": "2023-06-23",
                    "precio": 23.43
                }
            ],
            "Correos": [
                {
                    "fecha": "2023-06-23",
                    "precio": 42.55
                }
            ],
            "PeloPlanet": [
                {
                    "fecha": "2023-06-23",
                    "precio": 25.4
                }
            ],
            "Centro Integral Conchi Nieto": [
                {
                    "fecha": "2023-06-23",
                    "precio": 23.97
                }
            ],
            "Carethy.es": [
                {
                    "fecha": "2023-06-23",
                    "precio": 25.05
                }
            ],
            "Coserty.com": [
                {
                    "fecha": "2023-06-23",
                    "precio": 34.0
                }
            ]
        }
    },
    {
        "fecha": "2023-06-23",
        "nombre": "davines - champ\u00fa nutritivo naturaltech nourishing 1000 ml",
        "GSI": "12276963486079426675",
        "historicos": {
            "davines-ah.com": [
                {
                    "fecha": "2023-06-23",
                    "precio": 14.03
                }
            ],
            "Amazon.es - Seller": [
                {
                    "fecha": "2023-06-23",
                    "precio": 55.04
                }
            ],
            "anadeana": [
                {
                    "fecha": "2023-06-23",
                    "precio": 54.74
                }
            ],
            "Beauty Hair": [
                {
                    "fecha": "2023-06-23",
                    "precio": 51.99
                }
            ],
            ".Prohair Store": [
                {
                    "fecha": "2023-06-23",
                    "precio": 51.19
                }
            ],
            "Perfumes Club": [
                {
                    "fecha": "2023-06-23",
                    "precio": 50.13
                }
            ],
            "Cuidamos de tu Cabello": [
                {
                    "fecha": "2023-06-23",
                    "precio": 56.92
                }
            ],
            "Coserty.com": [
                {
                    "fecha": "2023-06-23",
                    "precio": 67.78
                }
            ]
        }
    },
    {
        "fecha": "2023-06-23",
        "nombre": "davines oi acondicionador 250 ml",
        "GSI": "9158348605555005549",
        "historicos": {
            "davines-ah.com": [
                {
                    "fecha": "2023-06-23",
                    "precio": 18.51
                }
            ],
            "anadeana": [
                {
                    "fecha": "2023-06-23",
                    "precio": 29.48
                }
            ],
            "Peluquer\u00eda Wapa\u00b4s": [
                {
                    "fecha": "2023-06-23",
                    "precio": 20.22
                }
            ],
            "Beauty Hair": [
                {
                    "fecha": "2023-06-23",
                    "precio": 23.2
                }
            ],
            "Perfumes Club": [
                {
                    "fecha": "2023-06-23",
                    "precio": 24.87
                }
            ],
            ".Prohair Store": [
                {
                    "fecha": "2023-06-23",
                    "precio": 29.43
                }
            ],
            "Sm The Beauty": [
                {
                    "fecha": "2023-06-23",
                    "precio": 33.54
                }
            ],
            "Carethy.es": [
                {
                    "fecha": "2023-06-23",
                    "precio": 33.91
                }
            ],
            "Cuidamos de tu Cabello": [
                {
                    "fecha": "2023-06-23",
                    "precio": 51.9
                }
            ],
            "Coserty.com": [
                {
                    "fecha": "2023-06-23",
                    "precio": 30.31
                }
            ]
        }
    },
    {
        "fecha": "2023-06-23",
        "nombre": "davines heart of glass rich conditioner 250 ml",
        "GSI": "8665728360764654241",
        "historicos": {
            "davines-ah.com": [
                {
                    "fecha": "2023-06-23",
                    "precio": 15.93
                }
            ],
            "anadeana": [
                {
                    "fecha": "2023-06-23",
                    "precio": 31.64
                }
            ],
            "todoparamipelo": [
                {
                    "fecha": "2023-06-23",
                    "precio": 22.29
                }
            ],
            "Beauty Hair": [
                {
                    "fecha": "2023-06-23",
                    "precio": 33.63
                }
            ],
            "EduardoSouto": [
                {
                    "fecha": "2023-06-23",
                    "precio": 28.48
                }
            ],
            "The Beauty Concept": [
                {
                    "fecha": "2023-06-23",
                    "precio": 31.28
                }
            ],
            "Perfumes Club": [
                {
                    "fecha": "2023-06-23",
                    "precio": 31.42
                }
            ],
            "Sm The Beauty": [
                {
                    "fecha": "2023-06-23",
                    "precio": 37.5
                }
            ],
            "Brasty.es": [
                {
                    "fecha": "2023-06-23",
                    "precio": 40.27
                }
            ],
            "Cuidamos de tu Cabello": [
                {
                    "fecha": "2023-06-23",
                    "precio": 39.82
                }
            ],
            "Coserty.com": [
                {
                    "fecha": "2023-06-23",
                    "precio": 25.9
                }
            ]
        }
    },
    {
        "fecha": "2023-06-23",
        "nombre": "davines - love curl acondicionador 1000ml",
        "GSI": "6025983038085933501",
        "historicos": {
            "davines-ah.com": [
                {
                    "fecha": "2023-06-23",
                    "precio": 13.63
                }
            ],
            "Amazon.es - Seller": [
                {
                    "fecha": "2023-06-23",
                    "precio": 81.03
                }
            ],
            "Beauty Hair": [
                {
                    "fecha": "2023-06-23",
                    "precio": 71.89
                }
            ],
            "Peluquer\u00eda Wapa\u00b4s": [
                {
                    "fecha": "2023-06-23",
                    "precio": 84.27
                }
            ],
            "todoparamipelo": [
                {
                    "fecha": "2023-06-23",
                    "precio": 59.16
                }
            ],
            "EduardoSouto": [
                {
                    "fecha": "2023-06-23",
                    "precio": 64.14
                }
            ],
            ".Prohair Store": [
                {
                    "fecha": "2023-06-23",
                    "precio": 79.23
                }
            ],
            "Perfumes Club": [
                {
                    "fecha": "2023-06-23",
                    "precio": 63.26
                }
            ],
            "Cuidamos de tu Cabello": [
                {
                    "fecha": "2023-06-23",
                    "precio": 85.57
                }
            ],
            "Coserty.com": [
                {
                    "fecha": "2023-06-23",
                    "precio": 109.01
                }
            ]
        }
    },
    {
        "fecha": "2023-06-23",
        "nombre": "davines naturaltech nourishing hair building pak 250 ml",
        "GSI": "11392259176749487154",
        "historicos": {
            "davines-ah.com": [
                {
                    "fecha": "2023-06-23",
                    "precio": 16.86
                }
            ],
            "anadeana": [
                {
                    "fecha": "2023-06-23",
                    "precio": 36.31
                }
            ],
            "Amazon.es - Seller": [
                {
                    "fecha": "2023-06-23",
                    "precio": 39.9
                }
            ],
            "EduardoSouto": [
                {
                    "fecha": "2023-06-23",
                    "precio": 34.44
                }
            ],
            "Beauty Hair": [
                {
                    "fecha": "2023-06-23",
                    "precio": 30.17
                }
            ],
            "Perfumes Club": [
                {
                    "fecha": "2023-06-23",
                    "precio": 40.83
                }
            ],
            "Sm The Beauty": [
                {
                    "fecha": "2023-06-23",
                    "precio": 41.92
                }
            ],
            "eBay - redlabeloutletltd": [
                {
                    "fecha": "2023-06-23",
                    "precio": 31.91
                }
            ],
            "Cuidamos de tu Cabello": [
                {
                    "fecha": "2023-06-23",
                    "precio": 69.19
                }
            ],
            "Coserty.com": [
                {
                    "fecha": "2023-06-23",
                    "precio": 47.72
                }
            ],
            "Miravia": [
                {
                    "fecha": "2023-06-23",
                    "precio": 28.37
                }
            ]
        }
    },
    {
        "fecha": "2023-06-23",
        "nombre": "davines minu acondicionador 1000 ml",
        "GSI": "9520454788893692575",
        "historicos": {
            "davines-ah.com": [
                {
                    "fecha": "2023-06-23",
                    "precio": 12.52
                }
            ],
            "Beauty Hair": [
                {
                    "fecha": "2023-06-23",
                    "precio": 74.76
                }
            ],
            "todoparamipelo": [
                {
                    "fecha": "2023-06-23",
                    "precio": 83.21
                }
            ],
            "EduardoSouto": [
                {
                    "fecha": "2023-06-23",
                    "precio": 73.33
                }
            ],
            ".Prohair Store": [
                {
                    "fecha": "2023-06-23",
                    "precio": 70.94
                }
            ],
            "Brasty.es": [
                {
                    "fecha": "2023-06-23",
                    "precio": 59.69
                }
            ],
            "Coserty.com": [
                {
                    "fecha": "2023-06-23",
                    "precio": 99.22
                }
            ]
        }
    },
    {
        "fecha": "2023-06-23",
        "nombre": "davines oi all in one milk 135 ml",
        "GSI": "9543312353508303797",
        "historicos": {
            "davines-ah.com": [
                {
                    "fecha": "2023-06-23",
                    "precio": 17.57
                }
            ],
            "anadeana": [
                {
                    "fecha": "2023-06-23",
                    "precio": 33.92
                }
            ],
            "Notino.es": [
                {
                    "fecha": "2023-06-23",
                    "precio": 37.68
                }
            ],
            "Peluquer\u00eda Wapa\u00b4s": [
                {
                    "fecha": "2023-06-23",
                    "precio": 29.41
                }
            ],
            "Beauty Hair": [
                {
                    "fecha": "2023-06-23",
                    "precio": 27.19
                }
            ],
            "EduardoSouto": [
                {
                    "fecha": "2023-06-23",
                    "precio": 35.72
                }
            ],
            ".Prohair Store": [
                {
                    "fecha": "2023-06-23",
                    "precio": 43.17
                }
            ],
            "The Beauty Concept": [
                {
                    "fecha": "2023-06-23",
                    "precio": 42.88
                }
            ],
            "Sm The Beauty": [
                {
                    "fecha": "2023-06-23",
                    "precio": 49.53
                }
            ],
            "hairllowers.com": [
                {
                    "fecha": "2023-06-23",
                    "precio": 35.79
                }
            ],
            "Coserty.com": [
                {
                    "fecha": "2023-06-23",
                    "precio": 27.57
                }
            ]
        }
    },
    {
        "fecha": "2023-06-23",
        "nombre": "davines oi oil 135 ml",
        "GSI": "8673629157721452512",
        "historicos": {
            "davines-ah.com": [
                {
                    "fecha": "2023-06-23",
                    "precio": 26.67
                }
            ],
            "Amazon.es - Seller": [
                {
                    "fecha": "2023-06-23",
                    "precio": 39.32
                }
            ],
            "anadeana": [
                {
                    "fecha": "2023-06-23",
                    "precio": 37.17
                }
            ],
            "Peluquer\u00eda Wapa\u00b4s": [
                {
                    "fecha": "2023-06-23",
                    "precio": 40.77
                }
            ],
            "Beauty Hair": [
                {
                    "fecha": "2023-06-23",
                    "precio": 50.34
                }
            ],
            "todoparamipelo": [
                {
                    "fecha": "2023-06-23",
                    "precio": 49.67
                }
            ],
            "EduardoSouto": [
                {
                    "fecha": "2023-06-23",
                    "precio": 36.91
                }
            ],
            ".Prohair Store": [
                {
                    "fecha": "2023-06-23",
                    "precio": 44.41
                }
            ],
            "Notino.es": [
                {
                    "fecha": "2023-06-23",
                    "precio": 40.99
                }
            ],
            "Sm The Beauty": [
                {
                    "fecha": "2023-06-23",
                    "precio": 40.47
                }
            ],
            "Tacha Beauty": [
                {
                    "fecha": "2023-06-23",
                    "precio": 53.83
                }
            ],
            "hairllowers.com": [
                {
                    "fecha": "2023-06-23",
                    "precio": 61.54
                }
            ],
            "Brasty.es": [
                {
                    "fecha": "2023-06-23",
                    "precio": 36.86
                }
            ],
            "Cuidamos de tu Cabello": [
                {
                    "fecha": "2023-06-23",
                    "precio": 48.52
                }
            ],
            "Coserty.com": [
                {
                    "fecha": "2023-06-23",
                    "precio": 39.48
                }
            ]
        }
    },
    {
        "fecha": "2023-06-23",
        "nombre": "davines oi hair butter 250 ml",
        "GSI": "9867941516065695162",
        "historicos": {
            "Amazon.es - Seller": [
                {
                    "fecha": "2023-06-23",
                    "precio": 39.07
                }
            ],
            "davines-ah.com": [
                {
                    "fecha": "2023-06-23",
                    "precio": 16.07
                }
            ],
            "anadeana": [
                {
                    "fecha": "2023-06-23",
                    "precio": 37.32
                }
            ],
            "Beauty Hair": [
                {
                    "fecha": "2023-06-23",
                    "precio": 24.83
                }
            ],
            "Peluquer\u00eda Wapa\u00b4s": [
                {
                    "fecha": "2023-06-23",
                    "precio": 22.9
                }
            ],
            "todoparamipelo": [
                {
                    "fecha": "2023-06-23",
                    "precio": 43.66
                }
            ],
            ".Prohair Store": [
                {
                    "fecha": "2023-06-23",
                    "precio": 35.35
                }
            ],
            "Sm The Beauty": [
                {
                    "fecha": "2023-06-23",
                    "precio": 46.61
                }
            ],
            "The Beauty Concept": [
                {
                    "fecha": "2023-06-23",
                    "precio": 57.55
                }
            ],
            "Perfumes Club": [
                {
                    "fecha": "2023-06-23",
                    "precio": 31.24
                }
            ],
            "Brasty.es": [
                {
                    "fecha": "2023-06-23",
                    "precio": 31.52
                }
            ],
            "Carethy.es": [
                {
                    "fecha": "2023-06-23",
                    "precio": 37.25
                }
            ],
            "Cuidamos de tu Cabello": [
                {
                    "fecha": "2023-06-23",
                    "precio": 46.98
                }
            ],
            "Coserty.com": [
                {
                    "fecha": "2023-06-23",
                    "precio": 33.11
                }
            ]
        }
    },
    {
        "fecha": "2023-06-23",
        "nombre": "davines nounou acondicionador 250 ml",
        "GSI": "9058111224963794474",
        "historicos": {
            "Famaideal": [
                {
                    "fecha": "2023-06-23",
                    "precio": 9.45
                }
            ],
            "todoparamipelo": [
                {
                    "fecha": "2023-06-23",
                    "precio": 25.86
                }
            ],
            "Beauty Hair": [
                {
                    "fecha": "2023-06-23",
                    "precio": 29.57
                }
            ],
            "EduardoSouto": [
                {
                    "fecha": "2023-06-23",
                    "precio": 26.72
                }
            ],
            ".Prohair Store": [
                {
                    "fecha": "2023-06-23",
                    "precio": 22.66
                }
            ]
        }
    },
    {
        "fecha": "2023-06-23",
        "nombre": "davines heart of glass silkening shampoo 250 ml",
        "GSI": "10011157393115561308",
        "historicos": {
            "davines-ah.com": [
                {
                    "fecha": "2023-06-23",
                    "precio": 17.64
                }
            ],
            "Amazon.es - Seller": [
                {
                    "fecha": "2023-06-23",
                    "precio": 18.09
                }
            ],
            "anadeana": [
                {
                    "fecha": "2023-06-23",
                    "precio": 30.92
                }
            ],
            "TuCabelloSano.com": [
                {
                    "fecha": "2023-06-23",
                    "precio": 28.0
                }
            ],
            "Notino.es": [
                {
                    "fecha": "2023-06-23",
                    "precio": 22.14
                }
            ],
            "todoparamipelo": [
                {
                    "fecha": "2023-06-23",
                    "precio": 27.59
                }
            ],
            "Beauty Hair": [
                {
                    "fecha": "2023-06-23",
                    "precio": 28.71
                }
            ],
            ".Prohair Store": [
                {
                    "fecha": "2023-06-23",
                    "precio": 24.03
                }
            ],
            "Noelia Jim\u00e9nez Shop": [
                {
                    "fecha": "2023-06-23",
                    "precio": 29.26
                }
            ],
            "Sm The Beauty": [
                {
                    "fecha": "2023-06-23",
                    "precio": 34.52
                }
            ],
            "Perfumes Club": [
                {
                    "fecha": "2023-06-23",
                    "precio": 25.68
                }
            ],
            "Coserty.com": [
                {
                    "fecha": "2023-06-23",
                    "precio": 29.09
                }
            ]
        }
    },
    {
        "fecha": "2023-06-23",
        "nombre": "davines replumping champ\u00fa 250 ml",
        "GSI": "14085577273259023259",
        "historicos": {
            "davines-ah.com": [
                {
                    "fecha": "2023-06-23",
                    "precio": 13.54
                }
            ],
            "TuCabelloSano.com": [
                {
                    "fecha": "2023-06-23",
                    "precio": 32.48
                }
            ],
            "Bellezasecret": [
                {
                    "fecha": "2023-06-23",
                    "precio": 16.41
                }
            ],
            "Beauty Hair": [
                {
                    "fecha": "2023-06-23",
                    "precio": 18.56
                }
            ],
            "Perfumes Club": [
                {
                    "fecha": "2023-06-23",
                    "precio": 21.63
                }
            ],
            "Peluquer\u00eda Wapa\u00b4s": [
                {
                    "fecha": "2023-06-23",
                    "precio": 26.25
                }
            ],
            "Famaideal": [
                {
                    "fecha": "2023-06-23",
                    "precio": 12.37
                }
            ],
            "The Beauty Concept": [
                {
                    "fecha": "2023-06-23",
                    "precio": 27.74
                }
            ],
            "Sm The Beauty": [
                {
                    "fecha": "2023-06-23",
                    "precio": 34.78
                }
            ],
            "hairllowers.com": [
                {
                    "fecha": "2023-06-23",
                    "precio": 29.51
                }
            ],
            "Correos": [
                {
                    "fecha": "2023-06-23",
                    "precio": 30.12
                }
            ],
            "Cuidamos de tu Cabello": [
                {
                    "fecha": "2023-06-23",
                    "precio": 27.79
                }
            ],
            "Coserty.com": [
                {
                    "fecha": "2023-06-23",
                    "precio": 34.38
                }
            ]
        }
    },
    {
        "fecha": "2023-06-23",
        "nombre": "davines more inside sea salt spray 250 ml",
        "GSI": "2667241078769520361",
        "historicos": {
            "Amazon.es - Seller": [
                {
                    "fecha": "2023-06-23",
                    "precio": 20.11
                }
            ],
            "davines-ah.com": [
                {
                    "fecha": "2023-06-23",
                    "precio": 14.03
                }
            ],
            "anadeana": [
                {
                    "fecha": "2023-06-23",
                    "precio": 34.22
                }
            ],
            "Peluquer\u00eda Wapa\u00b4s": [
                {
                    "fecha": "2023-06-23",
                    "precio": 22.75
                }
            ],
            "Beauty Hair": [
                {
                    "fecha": "2023-06-23",
                    "precio": 25.69
                }
            ],
            "Perfumes Club": [
                {
                    "fecha": "2023-06-23",
                    "precio": 23.73
                }
            ],
            "The Beauty Concept": [
                {
                    "fecha": "2023-06-23",
                    "precio": 31.81
                }
            ],
            ".Prohair Store": [
                {
                    "fecha": "2023-06-23",
                    "precio": 30.58
                }
            ],
            "hairllowers.com": [
                {
                    "fecha": "2023-06-23",
                    "precio": 33.71
                }
            ],
            "Correos": [
                {
                    "fecha": "2023-06-23",
                    "precio": 27.47
                }
            ],
            "Carethy.es": [
                {
                    "fecha": "2023-06-23",
                    "precio": 38.14
                }
            ],
            "Coserty.com": [
                {
                    "fecha": "2023-06-23",
                    "precio": 31.1
                }
            ],
            "Biuky.es": [
                {
                    "fecha": "2023-06-23",
                    "precio": 26.02
                }
            ]
        }
    },
    {
        "fecha": "2023-06-23",
        "nombre": "davines champ\u00fa nounou 75 ml",
        "GSI": "3476464378683291905",
        "historicos": {
            "Amazon.es - Seller": [
                {
                    "fecha": "2023-06-23",
                    "precio": 17.74
                }
            ],
            "todoparamipelo": [
                {
                    "fecha": "2023-06-23",
                    "precio": 15.87
                }
            ],
            "Perfumes Club": [
                {
                    "fecha": "2023-06-23",
                    "precio": 8.56
                }
            ],
            "Perfumeria.com": [
                {
                    "fecha": "2023-06-23",
                    "precio": 10.37
                }
            ],
            "Perfumerias.com": [
                {
                    "fecha": "2023-06-23",
                    "precio": 15.31
                }
            ],
            ".Prohair Store": [
                {
                    "fecha": "2023-06-23",
                    "precio": 12.99
                }
            ],
            "La Tienda de Cosm\u00e9ticos": [
                {
                    "fecha": "2023-06-23",
                    "precio": 16.55
                }
            ],
            "Brasty.es": [
                {
                    "fecha": "2023-06-23",
                    "precio": 25.76
                }
            ],
            "Coserty.com": [
                {
                    "fecha": "2023-06-23",
                    "precio": 11.07
                }
            ]
        }
    },
    {
        "fecha": "2023-06-23",
        "nombre": "davines more inside curl building serum - 250 ml",
        "GSI": "1050479297502208109",
        "historicos": {
            "davines-ah.com": [
                {
                    "fecha": "2023-06-23",
                    "precio": 21.46
                }
            ],
            "Amazon.es": [
                {
                    "fecha": "2023-06-23",
                    "precio": 34.74
                }
            ],
            "anadeana": [
                {
                    "fecha": "2023-06-23",
                    "precio": 29.95
                }
            ],
            "Beauty Hair": [
                {
                    "fecha": "2023-06-23",
                    "precio": 27.95
                }
            ],
            "Perfumes Club": [
                {
                    "fecha": "2023-06-23",
                    "precio": 25.11
                }
            ],
            "Noelia Jim\u00e9nez Shop": [
                {
                    "fecha": "2023-06-23",
                    "precio": 22.59
                }
            ],
            ".Prohair Store": [
                {
                    "fecha": "2023-06-23",
                    "precio": 31.59
                }
            ],
            "Sm The Beauty": [
                {
                    "fecha": "2023-06-23",
                    "precio": 27.38
                }
            ],
            "Correos": [
                {
                    "fecha": "2023-06-23",
                    "precio": 23.71
                }
            ],
            "hairllowers.com": [
                {
                    "fecha": "2023-06-23",
                    "precio": 39.19
                }
            ],
            "Cuidamos de tu Cabello": [
                {
                    "fecha": "2023-06-23",
                    "precio": 42.68
                }
            ],
            "eBay - tiendatayler": [
                {
                    "fecha": "2023-06-23",
                    "precio": 40.72
                }
            ]
        }
    },
    {
        "fecha": "2023-06-23",
        "nombre": "davines naturaltech purifying champ\u00fa 100 ml",
        "GSI": "813071008737609872",
        "historicos": {
            "anadeana": [
                {
                    "fecha": "2023-06-23",
                    "precio": 20.31
                }
            ],
            "Amazon.es - Seller": [
                {
                    "fecha": "2023-06-23",
                    "precio": 15.33
                }
            ],
            "todoparamipelo": [
                {
                    "fecha": "2023-06-23",
                    "precio": 14.13
                }
            ],
            "Perfumes Club": [
                {
                    "fecha": "2023-06-23",
                    "precio": 13.8
                }
            ],
            "davines-ah.com": [
                {
                    "fecha": "2023-06-23",
                    "precio": 20.26
                }
            ],
            "La Tienda de Cosm\u00e9ticos": [
                {
                    "fecha": "2023-06-23",
                    "precio": 13.98
                }
            ],
            "EduardoSouto": [
                {
                    "fecha": "2023-06-23",
                    "precio": 13.32
                }
            ],
            ".Prohair Store": [
                {
                    "fecha": "2023-06-23",
                    "precio": 8.97
                }
            ],
            "Sm The Beauty": [
                {
                    "fecha": "2023-06-23",
                    "precio": 16.98
                }
            ],
            "Brasty.es": [
                {
                    "fecha": "2023-06-23",
                    "precio": 16.4
                }
            ],
            "Cuidamos de tu Cabello": [
                {
                    "fecha": "2023-06-23",
                    "precio": 16.93
                }
            ],
            "Carethy.es": [
                {
                    "fecha": "2023-06-23",
                    "precio": 20.7
                }
            ],
            "Coserty.com": [
                {
                    "fecha": "2023-06-23",
                    "precio": 13.54
                }
            ],
            "Biuky.es": [
                {
                    "fecha": "2023-06-23",
                    "precio": 18.55
                }
            ],
            "Miravia": [
                {
                    "fecha": "2023-06-23",
                    "precio": 13.48
                }
            ]
        }
    },
    {
        "fecha": "2023-06-23",
        "nombre": "davines - melu acondicionador 1000ml",
        "GSI": "12414137775388458150",
        "historicos": {
            "davines-ah.com": [
                {
                    "fecha": "2023-06-23",
                    "precio": 12.88
                }
            ],
            "Amazon.es - Seller": [
                {
                    "fecha": "2023-06-23",
                    "precio": 77.13
                }
            ],
            "Notino.es": [
                {
                    "fecha": "2023-06-23",
                    "precio": 95.56
                }
            ],
            "Peluquer\u00eda Wapa\u00b4s": [
                {
                    "fecha": "2023-06-23",
                    "precio": 72.18
                }
            ],
            "todoparamipelo": [
                {
                    "fecha": "2023-06-23",
                    "precio": 75.57
                }
            ],
            "EduardoSouto": [
                {
                    "fecha": "2023-06-23",
                    "precio": 74.39
                }
            ],
            "Brasty.es": [
                {
                    "fecha": "2023-06-23",
                    "precio": 84.0
                }
            ],
            "Cuidamos de tu Cabello": [
                {
                    "fecha": "2023-06-23",
                    "precio": 80.64
                }
            ],
            "Coserty.com": [
                {
                    "fecha": "2023-06-23",
                    "precio": 76.01
                }
            ]
        }
    },
    {
        "fecha": "2023-06-23",
        "nombre": "davines energizing champ\u00fa 250ml",
        "GSI": "15525290041480229573",
        "historicos": {
            "Amazon.es - Seller": [
                {
                    "fecha": "2023-06-23",
                    "precio": 28.19
                }
            ],
            "anadeana": [
                {
                    "fecha": "2023-06-23",
                    "precio": 25.59
                }
            ],
            "Perfumes Club": [
                {
                    "fecha": "2023-06-23",
                    "precio": 29.58
                }
            ],
            "NeceserOnline": [
                {
                    "fecha": "2023-06-23",
                    "precio": 29.28
                }
            ],
            "Beauty Hair": [
                {
                    "fecha": "2023-06-23",
                    "precio": 20.08
                }
            ],
            "Peluquer\u00eda Wapa\u00b4s": [
                {
                    "fecha": "2023-06-23",
                    "precio": 20.16
                }
            ],
            "MyOrigines": [
                {
                    "fecha": "2023-06-23",
                    "precio": 21.39
                }
            ],
            "Noelia Jim\u00e9nez Shop": [
                {
                    "fecha": "2023-06-23",
                    "precio": 31.68
                }
            ],
            "The Beauty Concept": [
                {
                    "fecha": "2023-06-23",
                    "precio": 27.69
                }
            ],
            "hairllowers.com": [
                {
                    "fecha": "2023-06-23",
                    "precio": 30.78
                }
            ],
            "Worten": [
                {
                    "fecha": "2023-06-23",
                    "precio": 105.51
                }
            ],
            "Cuidamos de tu Cabello": [
                {
                    "fecha": "2023-06-23",
                    "precio": 40.1
                }
            ],
            "Coserty.com": [
                {
                    "fecha": "2023-06-23",
                    "precio": 22.29
                }
            ],
            "Miravia": [
                {
                    "fecha": "2023-06-23",
                    "precio": 34.34
                }
            ]
        }
    },
    {
        "fecha": "2023-06-23",
        "nombre": "davines renewing champ\u00fa 250 ml",
        "GSI": "14144590952505956890",
        "historicos": {
            "davines-ah.com": [
                {
                    "fecha": "2023-06-23",
                    "precio": 16.85
                }
            ],
            "Amazon.es - Seller": [
                {
                    "fecha": "2023-06-23",
                    "precio": 21.19
                }
            ],
            "anadeana": [
                {
                    "fecha": "2023-06-23",
                    "precio": 25.16
                }
            ],
            "Beauty Hair": [
                {
                    "fecha": "2023-06-23",
                    "precio": 18.89
                }
            ],
            "The Beauty Concept": [
                {
                    "fecha": "2023-06-23",
                    "precio": 25.1
                }
            ],
            "hairllowers.com": [
                {
                    "fecha": "2023-06-23",
                    "precio": 21.86
                }
            ],
            "Sm The Beauty": [
                {
                    "fecha": "2023-06-23",
                    "precio": 29.16
                }
            ],
            "Brasty.es": [
                {
                    "fecha": "2023-06-23",
                    "precio": 19.56
                }
            ],
            "Centro Integral Conchi Nieto": [
                {
                    "fecha": "2023-06-23",
                    "precio": 34.44
                }
            ],
            "Cuidamos de tu Cabello": [
                {
                    "fecha": "2023-06-23",
                    "precio": 28.67
                }
            ],
            "Coserty.com": [
                {
                    "fecha": "2023-06-23",
                    "precio": 31.13
                }
            ]
        }
    },
    {
        "fecha": "2023-06-23",
        "nombre": "davines champ\u00fa rebalancing 250 ml",
        "GSI": "3321539125099760305",
        "historicos": {
            "davines-ah.com": [
                {
                    "fecha": "2023-06-23",
                    "precio": 16.41
                }
            ],
            "anadeana": [
                {
                    "fecha": "2023-06-23",
                    "precio": 21.94
                }
            ],
            "TuCabelloSano.com": [
                {
                    "fecha": "2023-06-23",
                    "precio": 29.01
                }
            ],
            "Beauty Hair": [
                {
                    "fecha": "2023-06-23",
                    "precio": 24.18
                }
            ],
            "EduardoSouto": [
                {
                    "fecha": "2023-06-23",
                    "precio": 25.32
                }
            ],
            "Correos": [
                {
                    "fecha": "2023-06-23",
                    "precio": 40.9
                }
            ],
            "Brasty.es": [
                {
                    "fecha": "2023-06-23",
                    "precio": 24.27
                }
            ],
            "Carethy.es": [
                {
                    "fecha": "2023-06-23",
                    "precio": 26.89
                }
            ]
        }
    },
    {
        "fecha": "2023-06-23",
        "nombre": "davines alchemic champ\u00fa copper 280 ml",
        "GSI": "11206826918413678452",
        "historicos": {
            "Amazon.es - Seller": [
                {
                    "fecha": "2023-06-23",
                    "precio": 27.2
                }
            ],
            "primor.eu": [
                {
                    "fecha": "2023-06-23",
                    "precio": 31.24
                }
            ],
            "Primor": [
                {
                    "fecha": "2023-06-23",
                    "precio": 22.47
                }
            ],
            "todoparamipelo": [
                {
                    "fecha": "2023-06-23",
                    "precio": 26.19
                }
            ],
            "Peluquer\u00eda Wapa\u00b4s": [
                {
                    "fecha": "2023-06-23",
                    "precio": 27.94
                }
            ],
            "La Tienda de Cosm\u00e9ticos": [
                {
                    "fecha": "2023-06-23",
                    "precio": 23.02
                }
            ],
            "Hola Princesa": [
                {
                    "fecha": "2023-06-23",
                    "precio": 26.71
                }
            ],
            "Brasty.es": [
                {
                    "fecha": "2023-06-23",
                    "precio": 20.83
                }
            ],
            "Cuidamos de tu Cabello": [
                {
                    "fecha": "2023-06-23",
                    "precio": 39.52
                }
            ],
            "Coserty.com": [
                {
                    "fecha": "2023-06-23",
                    "precio": 20.87
                }
            ]
        }
    },
    {
        "fecha": "2023-06-23",
        "nombre": "davines melu champ\u00fa 250 ml",
        "GSI": "2530150965370143429",
        "historicos": {
            "Amazon.es - Seller": [
                {
                    "fecha": "2023-06-23",
                    "precio": 21.42
                }
            ],
            "anadeana": [
                {
                    "fecha": "2023-06-23",
                    "precio": 23.46
                }
            ],
            "Notino.es": [
                {
                    "fecha": "2023-06-23",
                    "precio": 26.08
                }
            ],
            "Perfumes Club": [
                {
                    "fecha": "2023-06-23",
                    "precio": 17.41
                }
            ],
            "Beauty Hair": [
                {
                    "fecha": "2023-06-23",
                    "precio": 18.94
                }
            ],
            "todoparamipelo": [
                {
                    "fecha": "2023-06-23",
                    "precio": 18.65
                }
            ],
            "EduardoSouto": [
                {
                    "fecha": "2023-06-23",
                    "precio": 25.41
                }
            ],
            ".Prohair Store": [
                {
                    "fecha": "2023-06-23",
                    "precio": 23.24
                }
            ],
            "The Beauty Concept": [
                {
                    "fecha": "2023-06-23",
                    "precio": 27.23
                }
            ],
            "luxciti.es": [
                {
                    "fecha": "2023-06-23",
                    "precio": 23.25
                }
            ],
            "hairllowers.com": [
                {
                    "fecha": "2023-06-23",
                    "precio": 24.92
                }
            ],
            "Brasty.es": [
                {
                    "fecha": "2023-06-23",
                    "precio": 27.67
                }
            ],
            "Cuidamos de tu Cabello": [
                {
                    "fecha": "2023-06-23",
                    "precio": 34.66
                }
            ],
            "Coserty.com": [
                {
                    "fecha": "2023-06-23",
                    "precio": 15.54
                }
            ],
            "fruugo.es": [
                {
                    "fecha": "2023-06-23",
                    "precio": 65.51
                }
            ]
        }
    },
    {
        "fecha": "2023-06-23",
        "nombre": "davines - love smoothing champ\u00fa 250ml",
        "GSI": "6667073508218113189",
        "historicos": {
            "Amazon.es - Seller": [
                {
                    "fecha": "2023-06-23",
                    "precio": 19.02
                }
            ],
            "anadeana": [
                {
                    "fecha": "2023-06-23",
                    "precio": 20.01
                }
            ],
            "EduardoSouto": [
                {
                    "fecha": "2023-06-23",
                    "precio": 20.41
                }
            ],
            "Noelia Jim\u00e9nez Shop": [
                {
                    "fecha": "2023-06-23",
                    "precio": 27.42
                }
            ],
            "The Beauty Concept": [
                {
                    "fecha": "2023-06-23",
                    "precio": 26.87
                }
            ],
            "Sm The Beauty": [
                {
                    "fecha": "2023-06-23",
                    "precio": 27.24
                }
            ],
            "hairllowers.com": [
                {
                    "fecha": "2023-06-23",
                    "precio": 29.97
                }
            ],
            "Brasty.es": [
                {
                    "fecha": "2023-06-23",
                    "precio": 17.68
                }
            ],
            "Cuidamos de tu Cabello": [
                {
                    "fecha": "2023-06-23",
                    "precio": 35.99
                }
            ]
        }
    },
    {
        "fecha": "2023-06-23",
        "nombre": "davines champ\u00fa calming 250 ml",
        "GSI": "10708395228749773555",
        "historicos": {
            "davines-ah.com": [
                {
                    "fecha": "2023-06-23",
                    "precio": 11.05
                }
            ],
            "Amazon.es - Seller": [
                {
                    "fecha": "2023-06-23",
                    "precio": 18.0
                }
            ],
            "anadeana": [
                {
                    "fecha": "2023-06-23",
                    "precio": 28.65
                }
            ],
            "TuCabelloSano.com": [
                {
                    "fecha": "2023-06-23",
                    "precio": 25.13
                }
            ],
            "Beauty Hair": [
                {
                    "fecha": "2023-06-23",
                    "precio": 23.73
                }
            ],
            "Peluquer\u00eda Wapa\u00b4s": [
                {
                    "fecha": "2023-06-23",
                    "precio": 24.28
                }
            ],
            "EduardoSouto": [
                {
                    "fecha": "2023-06-23",
                    "precio": 29.61
                }
            ],
            "MyOrigines": [
                {
                    "fecha": "2023-06-23",
                    "precio": 15.95
                }
            ],
            "hairllowers.com": [
                {
                    "fecha": "2023-06-23",
                    "precio": 32.68
                }
            ],
            "Sm The Beauty": [
                {
                    "fecha": "2023-06-23",
                    "precio": 30.34
                }
            ],
            "Correos": [
                {
                    "fecha": "2023-06-23",
                    "precio": 29.59
                }
            ],
            "Brasty.es": [
                {
                    "fecha": "2023-06-23",
                    "precio": 24.38
                }
            ],
            "Carethy.es": [
                {
                    "fecha": "2023-06-23",
                    "precio": 22.03
                }
            ],
            "Coserty.com": [
                {
                    "fecha": "2023-06-23",
                    "precio": 31.32
                }
            ],
            "Biuky.es": [
                {
                    "fecha": "2023-06-23",
                    "precio": 25.72
                }
            ]
        }
    }
]